{"version": "1", "message": "ERROR: Hidden Testcases server unreachable.", "problem_id": "ads2_m10_a1_1", "user_id": "rohith-22", "score": {"sample": {"0": {"execution_time": 0.41948509216308594, "passed": true}, "1": {"execution_time": 0.41483211517333984, "passed": true}, "2": {"execution_time": 0.36083102226257324, "passed": true}, "3": {"execution_time": 0.17731404304504395, "passed": false}, "4": {"execution_time": 0.6466069221496582, "passed": true}, "5": {"execution_time": 0.8267567157745361, "passed": true}, "6": {"execution_time": 2.6198582649230957, "passed": true}, "7": {"execution_time": 0.31986165046691895, "passed": true}, "8": {"execution_time": 2.1835618019104004, "passed": true}}}, "check_style_score": "0/1"}